turboxlsx-1.2.0.dist-info/METADATA
turboxlsx-1.2.0.dist-info/WHEEL
turboxlsx-1.2.0.dist-info/licenses/LICENSE
turboxlsx.libs/libgcc_s-e52197c3.so.1
turboxlsx/__init__.py
turboxlsx/turboxlsx.abi3.so
turboxlsx-1.2.0.dist-info/RECORD
