Metadata-Version: 2.4
Name: turboxlsx
Version: 1.2.0
Classifier: Programming Language :: Rust
Classifier: Programming Language :: Python :: Implementation :: CPython
Classifier: Programming Language :: Python :: Implementation :: PyPy
License-File: LICENSE
Requires-Python: >=3.8
Project-URL: Repository, https://github.com/GreyRaphael/turboxlsx
Project-URL: Changelog, https://github.com/GreyRaphael/turboxlsx/releases
